{"x6KXn95L2EvXXB2Prr9DeQ==":"don-bosco-photo.jpg","izUQ9j2Wvuy8fwZLcGDcaA==":"don%20bosco%20photo-1024x768.jpg","Q9dke7IqfXWjHW0v4BZY5A==":"don%20bosco%20college-183x170.jpg","gekulLuCP2l9FgBCH7d8+A==":"mbr-1920x1280.jpg","i+IaUKJTM1iEwOboQo6cYA==":"all%20logos-292x240.jpg","bkkrBSdI6ll6cv5jR05YOg==":"picture1-510x420.png","utzrr+l8S4MUXcLcJRPxOg==":"picture1-1209x995.png","z7t+83fYdgL2BLok+4QtlQ==":"don%20bosco%20college-122x113.jpg","yOdu+KNbUwXka3mDLUW5oA==":"mbr-1920x1371.jpg","MlaM/DojIPOyrgKjWG98AQ==":"mbr-1920x1277.jpg","3g95hGgRAQFJmGT2IRNPcQ==":"mbr-1-1920x1280.jpg","qmGzfFJjWPiq+TJP19aIUg==":"mbr-1920x1080.jpg","zJ7lHtZK9wiZdCFhyjyYJw==":"dr%20panchatcharam%20mariappan-300x382.jpg","g42QBUXkDIfNhI+tXvmCow==":"dr.%20sunita%20kumari-300x467.jpg","cTXuuiJ4yCzI9e6sn1hGkg==":"dr.%20jiban%20saikia-200x245.jpg","mL5/85Sc7I5rHj4A9gGIzw==":"dr%20vishal%20bharti-300x300.jpg","dsCqERLXkrG7XjUK0Er2gg==":"dr%20venky%20krishnan-120x120.jpg","JhCpGSLS3I2HLzJCwHF+aw==":"dr.%20tapan%20kr%20paul-198x255.jpg","mhEl1zxB3/ZM3OoFNf0Q7w==":"mbr-1920x1357.jpg","pa5Dkwo/T1qgW/t0h+fQvA==":"background5.jpg","eiZtNlHjX8zVmC6dhL4nfw==":"dr.%20rekha%20raja-300x300.jpg","hC7xHIlL8LW0Ur9RyleU5A==":"dr.%20rania%20mechergui-300x263.jpg","ZA9Ll/X2gyho19WveIrBTA==":"mrs%20%20saliha%20zerdoum-300x400.jpg","KZwn2MhM/fa4KhlBs8G9uQ==":"prof%20a%20d%20munshi-300x393.jpg","u3fZSJ4/S/gj+LD/JWg+BA==":"prof%20ranjit%20chaterjee-300x300.jpg","UhzuJjWiW+QP3MA4ilaxOg==":"mbr-1920x858.jpg","0dofov5ZNSB5zhfHLlBO1g==":"mbr-1920x1920.jpg","tjERxCO3gvHzFVtfcQ68ew==":"mbr-1-1920x1357.jpg","PLOgsnDW8IU036ExuLTNcQ==":"mbr-1-1920x1920.jpg","/NDd1qyFvxDmRfiPAm53oA==":"mbr-1920x1080.png","KAi3lfHeBskwfQb1iHNLRg==":"mbr-1920x1555.jpg","K9QCqTaR1C6DYLlbBtV+EQ==":"mbr-1920x1914.jpg","J2J1RAsxECZS9o57lkAoSQ==":"mbr-1920x1079.jpg","5OcuvGLfSaljYQR1hKvchQ==":"prof%20a%20d%20munshi-300x366.jpg","kG0UFwQ8EAIuO+pZ0WqneQ==":"prof%20ranjit%20chaterjee-300x314.jpg","tSt4C+F4Pyn7mxcvxf0g0g==":"mbr-1-1920x1080.jpg","uMy18mTdRmXAts73/dN8dg==":"qr%20code-300x300.png"}